Workbook
Name Slicer_Months__Date: #N/A
Name Slicer_PaymentMethod: #N/A
Name Slicer_Region: #N/A

Sheet Sheet2
A1: Date | B1: Region | C1: DeliveryDate | D1: ShippingCost | E1: UnitPrice | F1: StoreLocation | G1: CustomerType | H1: Discount | I1: Salesperson | J1: OrderDate | K1: PaymentMethod | L1: Returned | M1: OrderID | N1: CustomerName | O1: Quantity | P1: TotalPrice | Q1: Product2 | R1: RegionManager
A2: 44980 | B2: East | C2: 44984 | D2: 43.34 | E2: 163.6 | F2: Store B | G2: Wholesale | H2: 0 | I2: Eva | J2: 44980 | K2: Online | L2: 0 | M2: REG100000 | N2: Cust 6583 | O2: 14 | P2: 2290.4 | Q2: Laptop | R2: Eric
A3: 45645 | B3: South | C3: 45654 | D3: 5.3 | E3: 544.01 | F3: Store A | G3: Retail | H3: 0 | I3: Alice | J3: 45645 | K3: Gift Card | L3: 0 | M3: REG100001 | N3: Cust 2144 | O3: 1 | P3: 544.01 | Q3: Phone | R3: Sophie
A4: 45056 | B4: North | C4: 45065 | D4: 20.46 | E4: 346.18 | F4: Store B | G4: Wholesale | H4: 0.1 | I4: Alice | J4: 45056 | K4: Online | L4: 0 | M4: REG100002 | N4: Cust 5998 | O4: 14 | P4: 4361.868 | Q4: Desk | R4: Ryan
A5: 45714 | B5: Central | C5: 45718 | D5: 27.95 | E5: 384.82 | F5: Store A | G5: Wholesale | H5: 0.15 | I5: Frank | J5: 45714 | K5: Gift Card | L5: 0 | M5: REG100003 | N5: Cust 7136 | O5: 18 | P5: 5887.746 | Q5: Chair | R5: Cameron
A6: 45101 | B6: East | C6: 45104 | D6: 5.73 | E6: 237.76 | F6: Store C | G6: Retail | H6: 0 | I6: Carlos | J6: 45101 | K6: Online | L6: 0 | M6: REG100004 | N6: Cust 6506 | O6: 18 | P6: 4279.68 | Q6: Desk | R6: Eric
A7: 45342 | B7: Central | C7: 45352 | D7: 11.92 | E7: 385.09 | F7: Store D | G7: Wholesale | H7: 0.15 | I7: Diana | J7: 45342 | K7: Credit Card | L7: 0 | M7: REG100005 | N7: Cust 3909 | O7: 2 | P7: 654.653 | Q7: Monitor | R7: Cameron
A8: 44937 | B8: South | C8: 44940 | D8: 5.02 | E8: 17.5 | F8: Store C | G8: Retail | H8: 0.1 | I8: Alice | J8: 44937 | K8: Debit Card | L8: 0 | M8: REG100006 | N8: Cust 7887 | O8: 7 | P8: 110.25 | Q8: Chair | R8: Sophie
A9: 44935 | B9: Central | C9: 44937 | D9: 48.01 | E9: 330.22 | F9: Store C | G9: Wholesale | H9: 0.15 | I9: Carlos | J9: 44935 | K9: Cash | L9: 0 | M9: REG100007 | N9: Cust 5301 | O9: 3 | P9: 842.061 | Q9: Chair | R9: Cameron
A10: 45581 | B10: South | C10: 45583 | D10: 42.11 | E10: 432.04 | F10: Store D | G10: Wholesale | H10: 0.05 | I10: Bob | J10: 45581 | K10: Debit Card | L10: 1 | M10: REG100008 | N10: Cust 2284 | O10: 3 | P10: 1231.314 | Q10: Chair | R10: Sophie
A11: 45721 | B11: West | C11: 45729 | D11: 41.1 | E11: 323.28 | F11: Store D | G11: Retail | H11: 0.1 | I11: Frank | J11: 45721 | K11: Gift Card | L11: 0 | M11: REG100009 | N11: Cust 3732 | O11: 5 | P11: 1454.76 | Q11: Desk | R11: Wendy
A12: 45392 | B12: North | C12: 45399 | D12: 12.14 | E12: 523.29 | F12: Store B | G12: Wholesale | H12: 0.15 | I12: Eva | J12: 45392 | K12: Debit Card | L12: 0 | M12: REG100010 | N12: Cust 1462 | O12: 15 | P12: 6671.9475 | Q12: Desk | R12: Ryan
A13: 45485 | B13: East | C13: 45491 | D13: 44.89 | E13: 207.35 | F13: Store D | G13: Retail | H13: 0.1 | I13: Eva | J13: 45485 | K13: Gift Card | L13: 1 | M13: REG100011 | N13: Cust 4330 | O13: 19 | P13: 3545.685 | Q13: Phone | R13: Eric
... A100: 45438 | B100: West | C100: 45441 | D100: 43.46 | E100: 491.68 | F100: Store D | G100: Wholesale | H100: 0.15 | I100: Alice | J100: 45438 | K100: Online | L100: 1 | M100: REG100098 | N100: Cust 4384 | O100: 20 | P100: 8358.56 | Q100: Laptop | R100: Wendy

Sheet Advance_Formula
A1: VLOOKUP | F1: Index Match | I1: If Condition
A2: OrderID | B2: Product | C2: Quantity | D2: TotalPrice | F2: Max Purchase | G2: =MAX(Table1[OrderDate]) -> 45828 | I2: 2290.4 | J2: =IF(I2>2000,"High Price","Low Price") -> High Price
A3: REG100007 | B3: =VLOOKUP(A3,Sheet2!M:R,5,FALSE) -> Chair | C3: =VLOOKUP(A3,Sheet2!M:R,3,0) -> 3 | D3: =VLOOKUP(A3,Sheet2!M:R,4,FALSE) -> 842.061 | F3: OrderID | G3: =INDEX(Sheet2!M:M, MATCH(MAX(Sheet2!J:J), Sheet2!J:J, 0)) -> REG100037 | I3: 544.01 | J3: =IF(I3>2000,"High Price","Low Price") -> Low Price
A4: REG100025 | B4: =VLOOKUP(A4,Sheet2!M:R,5,FALSE) -> Phone | C4: =VLOOKUP(A4,Sheet2!M:R,3,0) -> 13 | D4: =VLOOKUP(A4,Sheet2!M:R,4,FALSE) -> 7309.77 | F4: CustomerName | G4: =INDEX(Sheet2!N:N, MATCH(MAX(Sheet2!J:J), Sheet2!J:J, 0)) -> Cust 3787 | I4: 4361.868 | J4: =IF(I4>2000,"High Price","Low Price") -> High Price
A5: REG100017 | B5: =VLOOKUP(A5,Sheet2!M:R,5,FALSE) -> Desk | C5: =VLOOKUP(A5,Sheet2!M:R,3,0) -> 11 | D5: =VLOOKUP(A5,Sheet2!M:R,4,FALSE) -> 5989.313 | I5: 5887.746 | J5: =IF(I5>2000,"High Price","Low Price") -> High Price
I6: 4279.68 | J6: =IF(I6>2000,"High Price","Low Price") -> High Price
I7: 654.653 | J7: =IF(I7>2000,"High Price","Low Price") -> Low Price
I8: 110.25 | J8: =IF(I8>2000,"High Price","Low Price") -> Low Price
I9: 842.061 | J9: =IF(I9>2000,"High Price","Low Price") -> Low Price
I10: 1231.314 | J10: =IF(I10>2000,"High Price","Low Price") -> Low Price
I11: 1454.76 | J11: =IF(I11>2000,"High Price","Low Price") -> Low Price
I12: 6671.9475 | J12: =IF(I12>2000,"High Price","Low Price") -> High Price
I13: 3545.685 | J13: =IF(I13>2000,"High Price","Low Price") -> High Price
I14: 114.5035 | J14: =IF(I14>2000,"High Price","Low Price") -> Low Price
I15: 134.1555 | J15: =IF(I15>2000,"High Price","Low Price") -> Low Price
I16: 2808.825 | J16: =IF(I16>2000,"High Price","Low Price") -> High Price
I17: 2631.804 | J17: =IF(I17>2000,"High Price","Low Price") -> High Price
... I100: 8358.56 | J100: =IF(I100>2000,"High Price","Low Price") -> High Price

Sheet Dashboard
A1: Sales Report Of - 2023,2024,2025

Sheet Region Vs TotalPrice
A3: Region | B3: Sum of TotalPrice
A4: Central | B4: 93552.871
A5: East | B5: 56705.127
A6: North | B6: 56432.545
A7: South | B7: 59673.343
A8: West | B8: 42490.722
A9: Grand Total | B9: 308854.61

Sheet Month Wise TotalPrice 
A3: Months (Date) | B3: Sum of TotalPrice
A4: Jan | B4: 35526.483
A5: Feb | B5: 37971.304
A6: Mar | B6: 41071.667
A7: Apr | B7: 27095.969
A8: May | B8: 36831.326
A9: Jun | B9: 22365.817
A10: Jul | B10: 18750.328
A11: Aug | B11: 6938.184
A12: Sep | B12: 6626.202
A13: Oct | B13: 27776.313
A14: Nov | B14: 26981.652
A15: Dec | B15: 20919.361
A16: Grand Total | B16: 308854.61

Sheet Product vs TotalPrice
A3: Product | B3: Sum of TotalPrice
A4: Chair | B4: 47507.756
A5: Desk | B5: 61269.576
A6: Laptop | B6: 55555.427
A7: Monitor | B7: 24137.04
A8: Phone | B8: 44999.143
A9: Printer | B9: 21996.18
A10: Tablet | B10: 53389.487
A11: Grand Total | B11: 308854.61

Sheet Region Vs Sum of Quantity
A3: Region | B3: Sum of Quantity
A4: Central | B4: 287
A5: East | B5: 217
A6: North | B6: 169
A7: South | B7: 180
A8: West | B8: 201
A9: Grand Total | B9: 1054

Sheet PaymentMethod vs TotalPrice
A3: PaymentMethod | B3: Sum of TotalPrice
A4: Cash | B4: 36578.336
A5: Credit Card | B5: 63489.49
A6: Debit Card | B6: 27929.256
A7: Gift Card | B7: 78911.626
A8: Online | B8: 101945.9
A9: Grand Total | B9: 308854.61
